metagame/__init__.py
metagame/py.typed
metagame/trading_client.py
metagame/websocket_api.py
metagame-0.4.16.dist-info/METADATA
metagame-0.4.16.dist-info/WHEEL
metagame-0.4.16.dist-info/RECORD
