Metadata-Version: 2.4
Name: metagame
Version: 0.4.16
Summary: MetaGame Trading Bootcamp Python Client
Author-email: Yoav Tzfati <yoav.tzfati@gmail.com>
Requires-Python: >=3.12
Requires-Dist: betterproto>=1.2.5
Requires-Dist: websockets>=14.2
